base.py
collpy.py
fancy.py
progressbar.py
collpy-0.0.4.dist-info/DESCRIPTION.rst
collpy-0.0.4.dist-info/METADATA
collpy-0.0.4.dist-info/RECORD
collpy-0.0.4.dist-info/WHEEL
collpy-0.0.4.dist-info/metadata.json
collpy-0.0.4.dist-info/top_level.txt
