Metadata-Version: 2.0
Name: collpy
Version: 0.0.4
Summary: Add color highlights, load bars, progress displays and style to your python scripts and shell sessions
Home-page: https://github.com/BlankGodd/collpy
Author: Damilare Agbabiaka (BlankGodd)
Author-email: blankgodd33@gmail.com
License: UNKNOWN
Project-URL: Bug Reports, https://github.com/BlankGodd/collpy/issues
Project-URL: Read the Docs, https://github.com/BlankGodd/collpy
Keywords: progress,loadbars,highlight,percentage,style,random,ansi
Platform: UNKNOWN
Classifier: Environment :: Console
Classifier: Intended Audience :: Developers
Classifier: Natural Language :: English
Classifier: Programming Language :: Python :: 3
Classifier: Programming Language :: Python :: 3.6
Classifier: Programming Language :: Python :: 3.7
Classifier: Programming Language :: Python :: 3.8
Classifier: Programming Language :: Python
Classifier: License :: OSI Approved :: MIT License
Classifier: Operating System :: OS Independent
Classifier: Topic :: Software Development :: Libraries :: Python Modules
Classifier: Topic :: Utilities
Classifier: Topic :: Home Automation
Classifier: Topic :: Multimedia :: Graphics
Classifier: Topic :: Terminals
Classifier: Topic :: Multimedia :: Graphics :: Presentation
Classifier: Topic :: Multimedia :: Graphics :: Viewers
Classifier: Topic :: Software Development :: Libraries :: Python Modules
Classifier: Topic :: Text Processing :: Filters
Classifier: Topic :: Text Processing :: Fonts
Classifier: Typing :: Typed
Requires-Python: >=3.6
